verilog/comps/IFUcomps/multiplexer.v
module muxnto1byn
#(parameter width = 8)
(
output reg[width-1:0]   out,
input    address,
input[width-1:0]   input0, input1
);

always @ (input0 or input1 or address) begin
      case (address)
         0 : out <= input0;
         1 : out <= input1;
      endcase
end
endmodule

verilog/comps/IFUcomps/register.v
module regPC(
  output[31:0] pctoalu,
  input[31:0] muxtopc,

  //output reg[31:0] PCaddress,
  input clk
);
reg [31:0]  memory={31'b0};
assign pctoalu = memory;
always @(posedge clk) begin
        memory <= muxtopc;
    end

endmodule

verilog/signextend.v
module signextend16

(
  input[15:0] in,
  output[31:0] extended
);
assign extended = {16'b0,in};
endmodule

module signextend26
(
   input [25:0]  in,
   output [31:0] extended
 );
	 // wire [29:0] 	 inter;
	 assign extended = {4'b0,in,2'b0};
	 // assign extended = {inter, 2'b0};
endmodule

module signextend16bne

(
  input[15:0] in,
  output[31:0] extended
);
assign extended = {14'b0,in,2'b0};
endmodule

verilog/comps/IFUcomps/adder.v
module adder
#(parameter width = 8)
(
    output[width-1:0] out,
    input[width-1:0] in0, in1
);

assign out = in0+in1;

endmodule

verilog/IFU.v
`include "comps/IFUcomps/multiplexer.v" // multiplexer
`include "comps/IFUcomps/signextend.v" // sign extend
`include "comps/IFUcomps/adder.v" // adder
`include "comps/IFUcomps/register.v"

module programcounter(
  output [31:0] pcaddress, // Output of Program Counter
  output [31:0] Reg_31, // Register 31
  input[15:0] branchaddress, // given branch address
  input[25:0] jumpaddress, // given branch address
  input jump, // is there a jump? yes or no. if not, just increment by 4
  input beq, // is BEQ true?
  input bne, // is BNE true?
  input regorimm, // is the incoming command from a register or immediate?
  input [31:0] Reg_rs, // Reg[rs]
  input reset, // reset command
  input clk

);
wire[31:0] alutomux; // line between ALU and mux
wire [31:0] muxtopc;// from mux to PC
wire [31:0] pctoalu;// PC to ALU
wire[31:0] beqbneadd; // adding branch address with PC + 4
wire[31:0] signextbranchaddr; // sign extended branch address
wire[31:0] signextjumpaddr; // sign extended jump address
wire[31:0] boutput; // output of mux that tests for BNE or BEQ
wire[31:0] intoOGmux; // wire entering main loop from regorimm output
wire outputofor; // input to BNE/BEQ multiplexer
reg[31:0] zeroinput; // 32-bit input of all zeros
reg[31:0] fourinput; // 32-bit input of just four (the number four in decimal)
reg resetreg; // address for reset multiplexer
wire[31:0] inputtopc; // output of reset multiplexer

// things that should be set initially
initial begin
  assign zeroinput = 32'b0;
  assign fourinput = 32'd4;
  assign resetreg = 1'b1;
end
// add output of PC with  4
adder #(.width(32)) addwithPC(.out(alutomux), .in0(fourinput), .in1(pctoalu));
// create a sign extended branch address
signextend16bne signextendbranchaddress(.extended(signextbranchaddr), .in(branchaddress));
// for bne and beq, doing PC + 4 + branchaddress
adder #(.width(32)) addPCwithbranchadd(.out(beqbneadd), .in0(signextbranchaddr), .in1(alutomux));
// seeing if beq or bne are on
or checkBNEBEQ(outputofor,beq, bne);
// sign extending jump address
signextend26 signextendjumpaddress(.extended(signextjumpaddr), .in(jumpaddress));
//setting the beq/bne or not multiplexer
muxnto1byn #(.width(32)) bnemulti(.out(boutput), .address(outputofor), .input0(alutomux),.input1(beqbneadd));
// setting multiplexer that checks if its a reg or an immediate
muxnto1byn #(.width(32)) regorimmmulti(.out(intoOGmux), .address(regorimm), .input0(signextjumpaddr),.input1(Reg_rs));
//setting OG multiplexer
muxnto1byn #(.width(32)) jumpmulti(.out(muxtopc), .address(jump), .input1(intoOGmux),.input0(boutput));
// setting the output of reg_31
assign Reg_31 = alutomux;
// creating the Program Counter (PC)
regPC pc(.pctoalu(pctoalu), .muxtopc(inputtopc),   .clk(clk));
// reset multiplexer, to reset the whole PC
muxnto1byn #(.width(32)) resetmulti(.out(inputtopc), .address(resetreg), .input1(zeroinput),.input0(muxtopc));
// Creating the output wire (output of PC) from an intermediate wire
assign  pcaddress = pctoalu;

//setting d flip-flop only on positive edge of clk
// to control reset
always @(reset) begin
  if(reset==1) begin
    //pcaddress <= 32'b0;
    assign resetreg = 1'b1;
  end
  else  begin
    assign resetreg = 1'b0;
  end
end
endmodule

verilog/IFU.t.v
// create module which will create an instantiation of the instructionfetchunit
// and then run test cases
`include "IFU.v"

module IFUtestbench();
  wire[31:0] pcaddress;
  wire[31:0] Reg_31;
  reg[25:0] jumpaddress;
  reg jump, beq, bne, regorimm,reset,Clk;
  reg[31:0] Reg_rs;
  reg[15:0] branchaddress;
  reg begintest;
  reg endtest;
  reg dutpassed;

// Instantiating testbench
  programcounter dut(
    .pcaddress(pcaddress),
    .Reg_31(Reg_31),
    .branchaddress(branchaddress),
    .jumpaddress(jumpaddress),
    .jump(jump),
    .beq(beq),
    .bne(bne),
    .regorimm(regorimm),
    .reset(reset),

    .Reg_rs(Reg_rs),
    .clk(Clk)
    );

    initial begin
      $dumpfile("IFU.vcd");
      $dumpvars();
      // The whole test is comprised of smaller tests, which are given sufficient time to run
      begintest=0;
      #10;
      begintest=1;
      #5000;
    end

    always @(posedge endtest) begin
      $display("DUT passed?: %b", dutpassed);
    end

    always @(posedge begintest) begin
      endtest = 0;
      dutpassed = 1;
      #10

      // Test Case 1 : Incrementing By 4 (Normal Operation Like Addi)
      #5 Clk=0;
      // resetting it, in order to be sure that the results are not dependent on previous values
      reset= 1'b1;
      // Giving it time to take effect (Only happens at the positive edge of the clock)
      #5 Clk=1; #5 Clk=0;
      #5 Clk=1;

      jumpaddress = 26'b0;
      branchaddress = 16'b0;
      jump = 1'b0;
      beq = 1'b0;
      bne = 1'b0;
      regorimm = 1'b0;
      reset= 1'b0;
      Reg_rs = 32'b0;
      // Giving it time to take effect
      #5 Clk=0; #5 Clk=1;#5 Clk=0;

      if(pcaddress !== 4) begin
        dutpassed = 0;
        $display("Test Case 1 Failed");
        $display("%b", pcaddress);
      end
      // Test Case 2 : jump

      // resetting it, to get consistent results
      reset= 1'b1;
      #5 Clk=1; #5 Clk=0;
      #5 Clk=5;
      jumpaddress = 26'd2;
      branchaddress = 16'd0;
      jump = 1'b1;
      beq = 1'b0;
      bne = 1'b0;
      regorimm = 1'b0;
      reset= 1'b0;
      Reg_rs = 32'b0;
      #5 Clk=0; #5 Clk=1;#5 Clk=0;

      if(pcaddress !== 2) begin
        dutpassed = 0;
        $display("Test Case 2 Failed");
        $display("%b", pcaddress);
      end
      // Test Case 3 : jal

      // resetting it
      reset= 1'b1;
      #5 Clk=1; #5 Clk=0;
      #5 Clk=1;

      jumpaddress = 26'd6;
      branchaddress = 16'd0;
      jump = 1'b1;
      beq = 1'b0;
      bne = 1'b0;
      regorimm = 1'b0;
      reset= 1'b0;
      Reg_rs = 32'b0;


      if(Reg_31 !== 32'd4) begin //reg_31 should be 4, because previos PC is 0, by reset
        dutpassed = 0;
        $display("Test Case 3 Failed, reg");
        $display("%b", Reg_31);
      end
      #5 Clk=0;#5 Clk=1;#5 Clk=0;
      if(pcaddress !== 6) begin
        dutpassed = 0;
        $display("Test Case 3 Failed, pcaddress");
        $display("%b", pcaddress);
      end
      // Test Case 4: jr

      // resetting it
      reset= 1'b1;
      #5 Clk=1; #5 Clk=0;

      jumpaddress = 26'd0;
      branchaddress = 16'b0;
      jump = 1'b1;
      beq = 1'b0;
      bne = 1'b0;
      regorimm = 1'b1;
      reset= 1'b0;
      Reg_rs = 32'd3;
      #5 Clk=0; #5 Clk=1;#5 Clk=0;

      if(pcaddress !== 3) begin
        dutpassed = 0;
        $display("Test Case 4 Failed");
        $display("%b", pcaddress);
      end
      // Test Case 5: beq

      // resetting it
      reset= 1'b1;
      #5 Clk=1; #5 Clk=0;#5 Clk=1;

      jumpaddress = 26'd2;
      branchaddress = 16'd15;
      jump = 1'b1;
      beq = 1'b1;
      bne = 1'b0;
      regorimm = 1'b0;
      reset= 1'b0;
      Reg_rs = 32'b0;
      #5 Clk=0; #5 Clk=1;#5 Clk=0;

      if(pcaddress !== 19) begin
        dutpassed = 0;
        $display("Test Case 5 Failed");
        $display("%b", pcaddress);
      end
      // Test Case 6: bne

      // resetting it
      reset= 1'b1;
      #5 Clk=1; #5 Clk=0; #5 Clk=1;

      jumpaddress = 26'd2;
      branchaddress = 16'd20;
      jump = 1'b1;
      beq = 1'b0;
      bne = 1'b1;
      regorimm = 1'b0;
      reset= 1'b0;
      Reg_rs = 32'b0;
      #5 Clk=0; #5 Clk=1;#5 Clk=0;
      if(pcaddress !== 24) begin
        dutpassed = 0;
        $display("Test Case 5 Failed");
        $display("%b", pcaddress);
      end

      #5
      endtest = 1;
      end
      endmodule

verilog/IFU.vcd
$date
	Mon Nov  4 03:15:30 2019
$end
$version
	Icarus Verilog
$end
$timescale
	1s
$end
$scope module IFUtestbench $end
$var wire 32 ! pcaddress [31:0] $end
$var wire 32 " Reg_31 [31:0] $end
$var reg 1 # Clk $end
$var reg 32 $ Reg_rs [31:0] $end
$var reg 1 % begintest $end
$var reg 1 & beq $end
$var reg 1 ' bne $end
$var reg 16 ( branchaddress [15:0] $end
$var reg 1 ) dutpassed $end
$var reg 1 * endtest $end
$var reg 1 + jump $end
$var reg 26 , jumpaddress [25:0] $end
$var reg 1 - regorimm $end
$var reg 1 . reset $end
$scope module dut $end
$var wire 32 / Reg_31 [31:0] $end
$var wire 32 0 Reg_rs [31:0] $end
$var wire 1 & beq $end
$var wire 1 ' bne $end
$var wire 16 1 branchaddress [15:0] $end
$var wire 1 # clk $end
$var wire 1 + jump $end
$var wire 26 2 jumpaddress [25:0] $end
$var wire 1 3 outputofor $end
$var wire 32 4 pcaddress [31:0] $end
$var wire 1 - regorimm $end
$var wire 1 . reset $end
$var wire 32 5 signextjumpaddr [31:0] $end
$var wire 32 6 signextbranchaddr [31:0] $end
$var wire 32 7 pctoalu [31:0] $end
$var wire 32 8 muxtopc [31:0] $end
$var wire 32 9 intoOGmux [31:0] $end
$var wire 32 : inputtopc [31:0] $end
$var wire 32 ; boutput [31:0] $end
$var wire 32 < beqbneadd [31:0] $end
$var wire 32 = alutomux [31:0] $end
$var reg 32 > fourinput [31:0] $end
$var reg 1 ? resetreg $end
$var reg 32 @ zeroinput [31:0] $end
$scope module addPCwithbranchadd $end
$var wire 32 A out [31:0] $end
$var wire 32 B in1 [31:0] $end
$var wire 32 C in0 [31:0] $end
$upscope $end
$scope module addwithPC $end
$var wire 32 D in0 [31:0] $end
$var wire 32 E out [31:0] $end
$var wire 32 F in1 [31:0] $end
$upscope $end
$scope module bnemulti $end
$var wire 1 3 address $end
$var wire 32 G input1 [31:0] $end
$var wire 32 H input0 [31:0] $end
$var reg 32 I out [31:0] $end
$upscope $end
$scope module jumpmulti $end
$var wire 1 + address $end
$var wire 32 J input0 [31:0] $end
$var wire 32 K input1 [31:0] $end
$var reg 32 L out [31:0] $end
$upscope $end
$scope module pc $end
$var wire 1 # clk $end
$var wire 32 M pctoalu [31:0] $end
$var wire 32 N muxtopc [31:0] $end
$var reg 32 O memory [31:0] $end
$upscope $end
$scope module regorimmmulti $end
$var wire 1 - address $end
$var wire 32 P input0 [31:0] $end
$var wire 32 Q input1 [31:0] $end
$var reg 32 R out [31:0] $end
$upscope $end
$scope module resetmulti $end
$var wire 1 ? address $end
$var wire 32 S input0 [31:0] $end
$var wire 32 T input1 [31:0] $end
$var reg 32 U out [31:0] $end
$upscope $end
$scope module signextendbranchaddress $end
$var wire 16 V in [15:0] $end
$var wire 32 W extended [31:0] $end
$upscope $end
$scope module signextendjumpaddress $end
$var wire 26 X in [25:0] $end
$var wire 32 Y extended [31:0] $end
$upscope $end
$upscope $end
$upscope $end
$enddefinitions $end
#0
$dumpvars
b0xxxxxxxxxxxxxxxxxxxxxxxxxx Y
bx X
b0xxxxxxxxxxxxxxxx W
bx V
b0 U
b0 T
bx S
bx R
bx Q
bx P
b0 O
b0 N
b0 M
bx L
bx K
b100 J
bx I
b0xxxxxxxxxxxxxxxxxxxxxxxxxx H
bx G
b0 F
b100 E
b100 D
b0xxxxxxxxxxxxxxxx C
b100 B
bx A
b0 @
1?
b100 >
b100 =
bx <
bx ;
b0 :
bx 9
bx 8
b0 7
b0xxxxxxxxxxxxxxxx 6
b0xxxxxxxxxxxxxxxxxxxxxxxxxx 5
b0 4
x3
bx 2
bx 1
bx 0
b100 /
x.
x-
bx ,
x+
x*
x)
bx (
x'
x&
0%
bx $
x#
b100 "
b0 !
$end
#10
1)
0*
1%
#25
1.
0#
#30
1#
#35
b0 9
b0 K
b0 R
b100 :
b100 N
b100 U
b0 ;
b0 I
b0 P
b100 8
b100 L
b100 S
0?
03
b0 $
b0 0
b0 Q
0.
0-
0'
0&
0+
b100 <
b100 A
b100 G
b0 6
b0 C
b0 W
b0 (
b0 1
b0 V
b0 5
b0 H
b0 Y
b0 ,
b0 2
b0 X
0#
#40
b1000 :
b1000 N
b1000 U
b1000 8
b1000 L
b1000 S
b1000 <
b1000 A
b1000 G
b1000 "
b1000 /
b1000 =
b1000 B
b1000 E
b1000 J
b100 !
b100 4
b100 7
b100 F
b100 M
b100 O
1#
#45
b0 :
b0 N
b0 U
1?
1.
0#
#50
b100 8
b100 L
b100 S
b100 <
b100 A
b100 G
b100 "
b100 /
b100 =
b100 B
b100 E
b100 J
b0 !
b0 4
b0 7
b0 F
b0 M
b0 O
1#
#55
b10 9
b10 K
b10 R
b10 :
b10 N
b10 U
b10 8
b10 L
b10 S
b10 ;
b10 I
b10 P
0?
0.
1+
b10 5
b10 H
b10 Y
b10 ,
b10 2
b10 X
0#
#60
b110 <
b110 A
b110 G
b110 "
b110 /
b110 =
b110 B
b110 E
b110 J
b10 !
b10 4
b10 7
b10 F
b10 M
b10 O
1#
#65
b0 :
b0 N
b0 U
1?
1.
0#
#70
b100 <
b100 A
b100 G
b100 "
b100 /
b100 =
b100 B
b100 E
b100 J
b0 !
b0 4
b0 7
b0 F
b0 M
b0 O
1#
#75
0#
#80
b110 8
b110 L
b110 S
b110 9
b110 K
b110 R
b110 :
b110 N
b110 U
b110 ;
b110 I
b110 P
0?
0.
b110 5
b110 H
b110 Y
b110 ,
b110 2
b110 X
1#
#85
0#
#90
b1010 <
b1010 A
b1010 G
b1010 "
b1010 /
b1010 =
b1010 B
b1010 E
b1010 J
b110 !
b110 4
b110 7
b110 F
b110 M
b110 O
1#
#95
b0 :
b0 N
b0 U
1?
1.
0#
#100
b100 <
b100 A
b100 G
b100 "
b100 /
b100 =
b100 B
b100 E
b100 J
b0 !
b0 4
b0 7
b0 F
b0 M
b0 O
1#
#105
b11 8
b11 L
b11 S
b11 :
b11 N
b11 U
b11 9
b11 K
b11 R
b0 ;
b0 I
b0 P
0?
b11 $
b11 0
b11 Q
0.
1-
b0 5
b0 H
b0 Y
b0 ,
b0 2
b0 X
0#
#110
b111 <
b111 A
b111 G
b111 "
b111 /
b111 =
b111 B
b111 E
b111 J
b11 !
b11 4
b11 7
b11 F
b11 M
b11 O
1#
#115
b0 :
b0 N
b0 U
1?
1.
0#
#120
b100 <
b100 A
b100 G
b100 "
b100 /
b100 =
b100 B
b100 E
b100 J
b0 !
b0 4
b0 7
b0 F
b0 M
b0 O
1#
#125
b10011 8
b10011 L
b10011 S
b10011 :
b10011 N
b10011 U
b10011 9
b10011 K
b10011 R
b10011 ;
b10011 I
b10011 P
0?
13
b0 $
b0 0
b0 Q
0.
0-
1&
b10011 <
b10011 A
b10011 G
b1111 6
b1111 C
b1111 W
b1111 (
b1111 1
b1111 V
b10 5
b10 H
b10 Y
b10 ,
b10 2
b10 X
0#
#130
b100110 :
b100110 N
b100110 U
b100110 8
b100110 L
b100110 S
b100110 9
b100110 K
b100110 R
b100110 ;
b100110 I
b100110 P
b100110 <
b100110 A
b100110 G
b10111 "
b10111 /
b10111 =
b10111 B
b10111 E
b10111 J
b10011 !
b10011 4
b10011 7
b10011 F
b10011 M
b10011 O
1#
#135
b0 :
b0 N
b0 U
1?
1.
0#
#140
b10011 8
b10011 L
b10011 S
b10011 9
b10011 K
b10011 R
b10011 ;
b10011 I
b10011 P
b10011 <
b10011 A
b10011 G
b100 "
b100 /
b100 =
b100 B
b100 E
b100 J
b0 !
b0 4
b0 7
b0 F
b0 M
b0 O
1#
#145
b11000 8
b11000 L
b11000 S
b11000 9
b11000 K
b11000 R
b11000 :
b11000 N
b11000 U
b11000 ;
b11000 I
b11000 P
0?
0.
1'
0&
b11000 <
b11000 A
b11000 G
b10100 6
b10100 C
b10100 W
b10100 (
b10100 1
b10100 V
0#
#150
b110000 :
b110000 N
b110000 U
b110000 8
b110000 L
b110000 S
b110000 9
b110000 K
b110000 R
b110000 ;
b110000 I
b110000 P
b110000 <
b110000 A
b110000 G
b11100 "
b11100 /
b11100 =
b11100 B
b11100 E
b11100 J
b11000 !
b11000 4
b11000 7
b11000 F
b11000 M
b11000 O
1#
#155
0#
#160
1*
